AUTHORS.rst
CHANGES.rst
MANIFEST.in
README.rst
TODO.rst
setup.cfg
setup.py
birdhousebuilder/__init__.py
birdhousebuilder.recipe.mongodb.egg-info/PKG-INFO
birdhousebuilder.recipe.mongodb.egg-info/SOURCES.txt
birdhousebuilder.recipe.mongodb.egg-info/dependency_links.txt
birdhousebuilder.recipe.mongodb.egg-info/entry_points.txt
birdhousebuilder.recipe.mongodb.egg-info/namespace_packages.txt
birdhousebuilder.recipe.mongodb.egg-info/not-zip-safe
birdhousebuilder.recipe.mongodb.egg-info/pbr.json
birdhousebuilder.recipe.mongodb.egg-info/requires.txt
birdhousebuilder.recipe.mongodb.egg-info/top_level.txt
birdhousebuilder/recipe/__init__.py
birdhousebuilder/recipe/mongodb/README.txt
birdhousebuilder/recipe/mongodb/__init__.py
birdhousebuilder/recipe/mongodb/mongod.conf
birdhousebuilder/recipe/mongodb/tests/__init__.py
birdhousebuilder/recipe/mongodb/tests/test_doctests.py