Metadata-Version: 1.1
Name: birdhousebuilder.recipe.mongodb
Version: 0.4.0
Summary: A Buildout recipe to install and setup mongodb with Anaconda.
Home-page: https://github.com/bird-house/birdhousebuilder.recipe.mongodb
Author: Birdhouse
Author-email: wps-dev at dkrz.de
License: Apache License 2
Keywords: buildout recipe birdhouse mongodb conda
Platform: UNKNOWN
Classifier: Framework :: Buildout
Classifier: Intended Audience :: Developers
Classifier: Topic :: Software Development :: Build Tools
Classifier: Topic :: Software Development :: Libraries :: Python Modules
Classifier: License :: OSI Approved :: BSD License
